pyzzen/__init__.py
pyzzen/__main__.py
pyzzen/admin_pass.py
pyzzen/quizz.py
pyzzen/server.py
pyzzen/static/custom.css
pyzzen/static/favicon.ico
pyzzen/static/simple.min.css
pyzzen/static/tex-mml-chtml.js
pyzzen/templates/admin.html
pyzzen/templates/base.html
pyzzen/templates/panel.html
pyzzen/templates/progress.html
pyzzen/templates/quizz_admin.html
pyzzen/templates/quizz_admin_end.html
pyzzen/templates/quizz_admin_start.html
pyzzen/templates/quizz_not_found.html
pyzzen/templates/quizz_user.html
pyzzen/templates/quizz_user_end.html
pyzzen/templates/quizz_user_start.html
pyzzen/templates/quizz_ws_reload.html
pyzzen/templates/username.html
pyzzen/translations/fr/LC_MESSAGES/messages.mo
pyzzen/translations/fr/LC_MESSAGES/messages.po
pyzzen-0.1.0.dist-info/WHEEL
pyzzen-0.1.0.dist-info/METADATA
pyzzen-0.1.0.dist-info/RECORD
