Metadata-Version: 2.1
Name: pyzzen
Version: 0.1.0
Summary: A small and simple self-hosted python quizz engine
Author-email: Arsène Volte <ninjananas@tuta.io>
Requires-Python: >=3.10
Classifier: Development Status :: 4 - Beta
Classifier: Programming Language :: Python :: 3 :: Only
Classifier: License :: OSI Approved :: MIT License
Classifier: Operating System :: OS Independent
Requires-Dist: toml; python_version < '3.11'
Requires-Dist: pydantic
Requires-Dist: quart
Requires-Dist: quart_babel
